RobotFrameworkService/Config.py
RobotFrameworkService/__init__.py
RobotFrameworkService/constants.py
RobotFrameworkService/main.py
RobotFrameworkService/version.py
RobotFrameworkService/requests/RobotOptions.py
RobotFrameworkService/requests/__init__.py
RobotFrameworkService/routers/__init__.py
RobotFrameworkService/routers/robotframework.py
RobotFrameworkService/routers/robotframework_run.py
robotframework_webservice-1.0.0.dist-info/LICENSE
robotframework_webservice-1.0.0.dist-info/METADATA
robotframework_webservice-1.0.0.dist-info/WHEEL
robotframework_webservice-1.0.0.dist-info/top_level.txt
robotframework_webservice-1.0.0.dist-info/RECORD
