Metadata-Version: 2.1
Name: robotframework-webservice
Version: 1.0.0
Summary: Webservice for running Robot Framework tasks
Home-page: https://github.com/MarketSquare/robotframework-webservice
Author: Markus Stahl
Classifier: Development Status :: 5 - Production/Stable
Classifier: License :: OSI Approved :: Apache Software License
Classifier: Operating System :: OS Independent
Classifier: Framework :: FastAPI
Classifier: Framework :: Robot Framework
Classifier: Programming Language :: Python :: 3.8
Classifier: Programming Language :: Python :: 3.9
Classifier: Programming Language :: Python :: 3.10
Classifier: Programming Language :: Python :: 3.11
Classifier: Programming Language :: Python :: 3.12
License-File: LICENSE
Requires-Dist: robotframework
Requires-Dist: fastapi
Requires-Dist: aiofiles
Requires-Dist: uvicorn
Requires-Dist: requests
